{
    "facets": [
        {
            "expression": "value",
            "columnName": "TMIN",
            "invert": false,
            "choices": [
                {
                    "v": {
                        "v": "22",
                        "l": "22"
                    },
                    "c": 2,
                    "s": false
                },
                {
                    "v": {
                        "v": "44",
                        "l": "44"
                    },
                    "c": 3,
                    "s": false
                },
                {
                    "v": {
                        "v": "45",
                        "l": "45"
                    },
                    "c": 2,
                    "s": false
                },
                {
                    "v": {
                        "v": "24",
                        "l": "24"
                    },
                    "c": 2,
                    "s": false
                },
                {
                    "v": {
                        "v": "25",
                        "l": "25"
                    },
                    "c": 3,
                    "s": false
                },
                {
                    "v": {
                        "v": "47",
                        "l": "47"
                    },
                    "c": 1,
                    "s": false
                },
                {
                    "v": {
                        "v": "26",
                        "l": "26"
                    },
                    "c": 1,
                    "s": false
                },
                {
                    "v": {
                        "v": "48",
                        "l": "48"
                    },
                    "c": 1,
                    "s": false
                },
                {
                    "v": {
                        "v": "27",
                        "l": "27"
                    },
                    "c": 5,
                    "s": false
                },
                {
                    "v": {
                        "v": "49",
                        "l": "49"
                    },
                    "c": 1,
                    "s": false
                },
                {
                    "v": {
                        "v": "28",
                        "l": "28"
                    },
                    "c": 6,
                    "s": false
                },
                {
                    "v": {
                        "v": "29",
                        "l": "29"
                    },
                    "c": 2,
                    "s": false
                },
                {
                    "v": {
                        "v": "50",
                        "l": "50"
                    },
                    "c": 3,
                    "s": false
                },
                {
                    "v": {
                        "v": "51",
                        "l": "51"
                    },
                    "c": 3,
                    "s": false
                },
                {
                    "v": {
                        "v": "30",
                        "l": "30"
                    },
                    "c": 7,
                    "s": false
                },
                {
                    "v": {
                        "v": "31",
                        "l": "31"
                    },
                    "c": 5,
                    "s": false
                },
                {
                    "v": {
                        "v": "32",
                        "l": "32"
                    },
                    "c": 5,
                    "s": false
                },
                {
                    "v": {
                        "v": "33",
                        "l": "33"
                    },
                    "c": 4,
                    "s": false
                },
                {
                    "v": {
                        "v": "11",
                        "l": "11"
                    },
                    "c": 1,
                    "s": false
                },
                {
                    "v": {
                        "v": "34",
                        "l": "34"
                    },
                    "c": 7,
                    "s": false
                },
                {
                    "v": {
                        "v": "12",
                        "l": "12"
                    },
                    "c": 1,
                    "s": false
                },
                {
                    "v": {
                        "v": "13",
                        "l": "13"
                    },
                    "c": 2,
                    "s": false
                },
                {
                    "v": {
                        "v": "35",
                        "l": "35"
                    },
                    "c": 3,
                    "s": false
                },
                {
                    "v": {
                        "v": "14",
                        "l": "14"
                    },
                    "c": 1,
                    "s": false
                },
                {
                    "v": {
                        "v": "36",
                        "l": "36"
                    },
                    "c": 4,
                    "s": false
                },
                {
                    "v": {
                        "v": "-1",
                        "l": "-1"
                    },
                    "c": 2,
                    "s": false
                },
                {
                    "v": {
                        "v": "15",
                        "l": "15"
                    },
                    "c": 1,
                    "s": false
                },
                {
                    "v": {
                        "v": "37",
                        "l": "37"
                    },
                    "c": 2,
                    "s": false
                },
                {
                    "v": {
                        "v": "38",
                        "l": "38"
                    },
                    "c": 3,
                    "s": false
                },
                {
                    "v": {
                        "v": "16",
                        "l": "16"
                    },
                    "c": 3,
                    "s": false
                },
                {
                    "v": {
                        "v": "17",
                        "l": "17"
                    },
                    "c": 1,
                    "s": false
                },
                {
                    "v": {
                        "v": "39",
                        "l": "39"
                    },
                    "c": 5,
                    "s": false
                },
                {
                    "v": {
                        "v": "18",
                        "l": "18"
                    },
                    "c": 1,
                    "s": false
                },
                {
                    "v": {
                        "v": "19",
                        "l": "19"
                    },
                    "c": 4,
                    "s": false
                },
                {
                    "v": {
                        "v": "-6",
                        "l": "-6"
                    },
                    "c": 1,
                    "s": false
                },
                {
                    "v": {
                        "v": "3",
                        "l": "3"
                    },
                    "c": 2,
                    "s": false
                },
                {
                    "v": {
                        "v": "4",
                        "l": "4"
                    },
                    "c": 1,
                    "s": false
                },
                {
                    "v": {
                        "v": "5",
                        "l": "5"
                    },
                    "c": 1,
                    "s": false
                },
                {
                    "v": {
                        "v": "6",
                        "l": "6"
                    },
                    "c": 1,
                    "s": false
                },
                {
                    "v": {
                        "v": "8",
                        "l": "8"
                    },
                    "c": 2,
                    "s": false
                },
                {
                    "v": {
                        "v": "60",
                        "l": "60"
                    },
                    "c": 1,
                    "s": false
                },
                {
                    "v": {
                        "v": "61",
                        "l": "61"
                    },
                    "c": 1,
                    "s": false
                },
                {
                    "v": {
                        "v": "40",
                        "l": "40"
                    },
                    "c": 6,
                    "s": false
                },
                {
                    "v": {
                        "v": "41",
                        "l": "41"
                    },
                    "c": 2,
                    "s": false
                },
                {
                    "v": {
                        "v": "42",
                        "l": "42"
                    },
                    "c": 3,
                    "s": false
                },
                {
                    "v": {
                        "v": "21",
                        "l": "21"
                    },
                    "c": 1,
                    "s": false
                },
                {
                    "v": {
                        "v": "43",
                        "l": "43"
                    },
                    "c": 1,
                    "s": false
                }
            ],
            "name": "TMIN"
        }
    ],
    "engine-mode": "row-based"
}